stactools/sentinel1_grd/__init__.py
stactools/sentinel1_grd/bands.py
stactools/sentinel1_grd/commands.py
stactools/sentinel1_grd/constants.py
stactools/sentinel1_grd/metadata_links.py
stactools/sentinel1_grd/product_metadata.py
stactools/sentinel1_grd/properties.py
stactools/sentinel1_grd/stac.py
stactools_sentinel1_grd-0.1.1.dist-info/LICENSE
stactools_sentinel1_grd-0.1.1.dist-info/METADATA
stactools_sentinel1_grd-0.1.1.dist-info/WHEEL
stactools_sentinel1_grd-0.1.1.dist-info/top_level.txt
stactools_sentinel1_grd-0.1.1.dist-info/RECORD
