Metadata-Version: 2.1
Name: stactools-sentinel1-grd
Version: 0.1.1
Summary: Stactools package for Sentinel-1 GRD scenes
Home-page: https://github.com/maximlamare/sentinel1-grd
Author: Maxim Lamare
Author-email: maxim.lamare@sentinel-hub.com
License: UNKNOWN
Project-URL: Issues, https://github.com/maximlamare/sentinel1-grd/issues
Keywords: stactools,pystac,catalog,STAC,sentinel,GRD,radar
Platform: UNKNOWN
Classifier: Development Status :: 4 - Beta
Classifier: License :: OSI Approved :: Apache Software License
Classifier: Programming Language :: Python :: 3.7
Classifier: Programming Language :: Python :: 3.8
Classifier: Programming Language :: Python :: 3.9
License-File: LICENSE
Requires-Dist: stactools (==0.2.1)
